icdr/__init__.py
icdr/icdr.dll
icdr/icdr.so
icdr/icdr_base.py
icdr/icdr_class.py
icdr/icdr_types.py
icdr/libgcc_s_seh-1.dll
icdr/libstdc++-6.dll
icdr/test_local.py
icdr-0.0.12.dist-info/licenses/LICENSE
icdr-0.0.12.dist-info/METADATA
icdr-0.0.12.dist-info/WHEEL
icdr-0.0.12.dist-info/top_level.txt
icdr-0.0.12.dist-info/RECORD
