Metadata-Version: 2.4
Name: icdr
Version: 0.0.12
Summary: DESCRIPTION
Home-page: https://github.com/lakritidis/icdr
Author: Leonidas Akritidis
Author-email: Leonidas Akritidis <lakritidis@ihu.gr>
Maintainer: Leonidas Akritidis
Maintainer-email: Leonidas Akritidis <lakritidis@ihu.gr>
License-Expression: Apache-2.0
Project-URL: Homepage, https://github.com/lakritidis/icdr
Project-URL: Issues, https://github.com/lakritidis/icdr/issues
Keywords: index,inverted index,contrastive data,pairs,information retrieval,similarity search,search,string search,approximate retrieval
Classifier: Programming Language :: Python :: 3
Classifier: Operating System :: OS Independent
Requires-Python: >=3.9
License-File: LICENSE
Requires-Dist: pandas
Dynamic: author
Dynamic: home-page
Dynamic: license-file
Dynamic: maintainer
